setup.py
mauscope/__init__.py
mauscope.egg-info/PKG-INFO
mauscope.egg-info/SOURCES.txt
mauscope.egg-info/dependency_links.txt
mauscope.egg-info/requires.txt
mauscope.egg-info/top_level.txt