Metadata-Version: 1.1
Name: mauscope
Version: 1.0.1
Summary: Microscopy stage.
Home-page: UNKNOWN
Author: Juan Barbosa
Author-email: js.barbosa10@uniandes.edu.co
License: GPL
Keywords: example documentation tutorial
Platform: UNKNOWN
Classifier: Development Status :: 1 - Planning
Classifier: Topic :: Utilities
Classifier: License :: OSI Approved :: GNU General Public License (GPL)
